minimalrequest/__init__.py
minimalrequest/minimal_request.py
minimalrequest/rate_limiter.py
minimalrequest-2.0.2.dist-info/LICENSE.txt
minimalrequest-2.0.2.dist-info/METADATA
minimalrequest-2.0.2.dist-info/WHEEL
minimalrequest-2.0.2.dist-info/top_level.txt
minimalrequest-2.0.2.dist-info/RECORD
