Metadata-Version: 2.1
Name: minimalrequest
Version: 2.0.2
Summary: Minimal Request Finder is a analysis tool to determine the minimum valid API request data (including headers, query params, and payload) required to receive a valid response from an endpoint. It is designed to help in the process of reverse engineering complex third party API's and identifying the smallest, most efficient request that can be made.
Author: Erik Bierbrauer
Project-URL: Homepage, https://github.com/ebier92/minimalrequest
Project-URL: Bug Tracker, https://github.com/ebier92/minimalrequest/issues
Classifier: Programming Language :: Python :: 3
Classifier: License :: OSI Approved :: Apache Software License
Classifier: Operating System :: OS Independent
Requires-Python: >=3.12
License-File: LICENSE.txt
Requires-Dist: httpx ==0.27.2
Requires-Dist: curlparser ==0.1.0
